README.md
setup.py
example_package_MITM/_init_.py
example_package_MITM/example.py
example_package_MITM.egg-info/PKG-INFO
example_package_MITM.egg-info/SOURCES.txt
example_package_MITM.egg-info/dependency_links.txt
example_package_MITM.egg-info/top_level.txt